{
	"nobike": {
		"0_0": 0,
		"0_1": 6,
		"0_2": 0,
		"0_3": 0,
		"0_4": 0,
		"0_5": 0,
		"0_6": 0,
		"0_7": 0,
		"0_8": 0,
		"0_9": 0,
		"0_10": 23,
		"0_11": 1,
		"0_12": 0,
		"0_13": 0,
		"0_14": 0,
		"0_15": 0,
		"0_16": 0,
		"0_17": 0,
		"0_18": 0,
		"0_19": 0,
		"0_20": 0,
		"0_21": 0,
		"0_22": 0,
		"0_23": 0,
		"1_0": 39,
		"1_1": 99,
		"1_2": 80,
		"1_3": 37,
		"1_4": 9,
		"1_5": 3,
		"1_6": 0,
		"1_7": 0,
		"1_8": 0,
		"1_9": 0,
		"1_10": 0,
		"1_11": 0,
		"1_12": 0,
		"1_13": 0,
		"1_14": 0,
		"1_15": 0,
		"1_16": 0,
		"1_17": 0,
		"1_18": 0,
		"1_19": 0,
		"1_20": 0,
		"1_21": 0,
		"1_22": 0,
		"1_23": 0,
		"2_0": 7,
		"2_1": 87,
		"2_2": 107,
		"2_3": 47,
		"2_4": 28,
		"2_5": 47,
		"2_6": 3,
		"2_7": 0,
		"2_8": 0,
		"2_9": 19,
		"2_10": 0,
		"2_11": 5,
		"2_12": 0,
		"2_13": 0,
		"2_14": 0,
		"2_15": 0,
		"2_16": 0,
		"2_17": 0,
		"2_18": 0,
		"2_19": 0,
		"2_20": 0,
		"2_21": 0,
		"2_22": 0,
		"2_23": 0,
		"3_0": 42,
		"3_1": 46,
		"3_2": 25,
		"3_3": 0,
		"3_4": 0,
		"3_5": 0,
		"3_6": 11,
		"3_7": 8,
		"3_8": 17,
		"3_9": 0,
		"3_10": 0,
		"3_11": 0,
		"3_12": 0,
		"3_13": 6,
		"3_14": 3,
		"3_15": 0,
		"3_16": 0,
		"3_17": 0,
		"3_18": 0,
		"3_19": 0,
		"3_20": 0,
		"3_21": 0,
		"3_22": 0,
		"3_23": 0,
		"4_0": 3,
		"4_1": 29,
		"4_2": 33,
		"4_3": 26,
		"4_4": 10,
		"4_5": 42,
		"4_6": 15,
		"4_7": 0,
		"4_8": 0,
		"4_9": 0,
		"4_10": 0,
		"4_11": 0,
		"4_12": 0,
		"4_13": 0,
		"4_14": 0,
		"4_15": 0,
		"4_16": 0,
		"4_17": 0,
		"4_18": 0,
		"4_19": 0,
		"4_20": 0,
		"4_21": 0,
		"4_22": 0,
		"4_23": 0,
		"5_0": 19,
		"5_1": 58,
		"5_2": 59,
		"5_3": 6,
		"5_4": 0,
		"5_5": 8,
		"5_6": 18,
		"5_7": 0,
		"5_8": 0,
		"5_9": 0,
		"5_10": 0,
		"5_11": 0,
		"5_12": 0,
		"5_13": 0,
		"5_14": 0,
		"5_15": 0,
		"5_16": 0,
		"5_17": 0,
		"5_18": 0,
		"5_19": 0,
		"5_20": 0,
		"5_21": 0,
		"5_22": 0,
		"5_23": 0,
		"6_0": 6,
		"6_1": 24,
		"6_2": 0,
		"6_3": 0,
		"6_4": 0,
		"6_5": 0,
		"6_6": 0,
		"6_7": 0,
		"6_8": 0,
		"6_9": 0,
		"6_10": 8,
		"6_11": 7,
		"6_12": 0,
		"6_13": 0,
		"6_14": 0,
		"6_15": 0,
		"6_16": 0,
		"6_17": 0,
		"6_18": 0,
		"6_19": 0,
		"6_20": 0,
		"6_21": 0,
		"6_22": 0,
		"6_23": 0
	},
	"nospace": {
		"0_0": 13,
		"0_1": 112,
		"0_2": 90,
		"0_3": 65,
		"0_4": 42,
		"0_5": 95,
		"0_6": 258,
		"0_7": 213,
		"0_8": 431,
		"0_9": 390,
		"0_10": 233,
		"0_11": 146,
		"0_12": 259,
		"0_13": 306,
		"0_14": 311,
		"0_15": 180,
		"0_16": 150,
		"0_17": 296,
		"0_18": 234,
		"0_19": 220,
		"0_20": 429,
		"0_21": 356,
		"0_22": 198,
		"0_23": 46,
		"1_0": 15,
		"1_1": 6,
		"1_2": 0,
		"1_3": 47,
		"1_4": 104,
		"1_5": 45,
		"1_6": 85,
		"1_7": 75,
		"1_8": 151,
		"1_9": 437,
		"1_10": 442,
		"1_11": 279,
		"1_12": 374,
		"1_13": 609,
		"1_14": 623,
		"1_15": 347,
		"1_16": 216,
		"1_17": 380,
		"1_18": 385,
		"1_19": 425,
		"1_20": 468,
		"1_21": 378,
		"1_22": 154,
		"1_23": 40,
		"2_0": 25,
		"2_1": 0,
		"2_2": 0,
		"2_3": 0,
		"2_4": 9,
		"2_5": 14,
		"2_6": 84,
		"2_7": 118,
		"2_8": 141,
		"2_9": 369,
		"2_10": 234,
		"2_11": 289,
		"2_12": 521,
		"2_13": 482,
		"2_14": 484,
		"2_15": 400,
		"2_16": 297,
		"2_17": 340,
		"2_18": 199,
		"2_19": 337,
		"2_20": 378,
		"2_21": 443,
		"2_22": 224,
		"2_23": 0,
		"3_0": 0,
		"3_1": 0,
		"3_2": 0,
		"3_3": 3,
		"3_4": 17,
		"3_5": 34,
		"3_6": 56,
		"3_7": 109,
		"3_8": 140,
		"3_9": 410,
		"3_10": 237,
		"3_11": 176,
		"3_12": 281,
		"3_13": 348,
		"3_14": 437,
		"3_15": 212,
		"3_16": 213,
		"3_17": 381,
		"3_18": 280,
		"3_19": 311,
		"3_20": 406,
		"3_21": 413,
		"3_22": 147,
		"3_23": 28,
		"4_0": 11,
		"4_1": 0,
		"4_2": 36,
		"4_3": 79,
		"4_4": 67,
		"4_5": 55,
		"4_6": 67,
		"4_7": 59,
		"4_8": 234,
		"4_9": 363,
		"4_10": 400,
		"4_11": 346,
		"4_12": 430,
		"4_13": 503,
		"4_14": 599,
		"4_15": 363,
		"4_16": 391,
		"4_17": 420,
		"4_18": 456,
		"4_19": 709,
		"4_20": 681,
		"4_21": 505,
		"4_22": 200,
		"4_23": 22,
		"5_0": 11,
		"5_1": 0,
		"5_2": 10,
		"5_3": 41,
		"5_4": 49,
		"5_5": 47,
		"5_6": 127,
		"5_7": 206,
		"5_8": 227,
		"5_9": 278,
		"5_10": 230,
		"5_11": 138,
		"5_12": 263,
		"5_13": 527,
		"5_14": 460,
		"5_15": 452,
		"5_16": 412,
		"5_17": 478,
		"5_18": 384,
		"5_19": 458,
		"5_20": 584,
		"5_21": 498,
		"5_22": 418,
		"5_23": 43,
		"6_0": 60,
		"6_1": 50,
		"6_2": 68,
		"6_3": 251,
		"6_4": 253,
		"6_5": 300,
		"6_6": 275,
		"6_7": 290,
		"6_8": 363,
		"6_9": 297,
		"6_10": 167,
		"6_11": 154,
		"6_12": 244,
		"6_13": 260,
		"6_14": 371,
		"6_15": 274,
		"6_16": 274,
		"6_17": 273,
		"6_18": 393,
		"6_19": 319,
		"6_20": 316,
		"6_21": 364,
		"6_22": 221,
		"6_23": 63
	}
}